lockr/cli/__init__.py
lockr/cli/__main__.py
lockr/cli/commands.py
lockr/cli/lockr.ini
lockr/lockr/__init__.py
lockr/lockr/constants.py
lockr/lockr/core.py
lockr-0.1.6.dist-info/METADATA
lockr-0.1.6.dist-info/WHEEL
lockr-0.1.6.dist-info/entry_points.txt
lockr-0.1.6.dist-info/RECORD
