Metadata-Version: 2.4
Name: lockr
Version: 0.1.6
Summary: A simple python CLI application, providing out-of-the-box Redis locking pattern for management of distributed applications in cloud.
License: MIT
Author: Paarth Bhasin
Author-email: paarthbhasin4@gmail.com
Requires-Python: >=3.9.22
Classifier: License :: OSI Approved :: MIT License
Classifier: Programming Language :: Python :: 3
Classifier: Programming Language :: Python :: 3.10
Classifier: Programming Language :: Python :: 3.11
Classifier: Programming Language :: Python :: 3.12
Classifier: Programming Language :: Python :: 3.13
Classifier: Programming Language :: Python :: 3.14
Requires-Dist: click (>=8.1.7,<9.0.0)
Requires-Dist: fakeredis (==2.32.1)
Requires-Dist: poetry-core (>=2.0.0,<3.0.0)
Requires-Dist: redis (==4.3.1)
Requires-Dist: requests (==2.27.1)
Project-URL: Homepage, https://github.com/PaarthB/LockR
